syntheticgen/SyntheticGen.py
syntheticgen/__init__.py
SyntheticGen-0.1.1.dist-info/LICENSE
SyntheticGen-0.1.1.dist-info/METADATA
SyntheticGen-0.1.1.dist-info/WHEEL
SyntheticGen-0.1.1.dist-info/top_level.txt
SyntheticGen-0.1.1.dist-info/RECORD
