Metadata-Version: 2.1
Name: SyntheticGen
Version: 0.1.1
Summary: Synthetic dataset creator/augmentor for machine learning applications.
Home-page: https://github.com/jf225/SyntheticGen
Author: James Fahey
Author-email: <jamesaf36@gmail.com>
License: MIT
Keywords: python,machine learning,data augmentation,sythetic datasets
Classifier: Development Status :: 3 - Alpha
Classifier: Intended Audience :: Developers
Classifier: Intended Audience :: Science/Research
Classifier: Programming Language :: Python :: 3
Classifier: License :: OSI Approved :: MIT License
Classifier: Operating System :: Unix
Classifier: Operating System :: MacOS :: MacOS X
Classifier: Operating System :: Microsoft :: Windows
License-File: LICENSE
Requires-Dist: numpy >=1.26.1
